volleystats/__init__.py
volleystats/items.py
volleystats/main.py
volleystats/middlewares.py
volleystats/pipelines.py
volleystats/settings.py
volleystats/utils.py
volleystats/version.py
volleystats/spiders/__init__.py
volleystats/spiders/competition.py
volleystats/spiders/match.py
volleystats-0.8.1.dist-info/LICENSE.md
volleystats-0.8.1.dist-info/METADATA
volleystats-0.8.1.dist-info/WHEEL
volleystats-0.8.1.dist-info/entry_points.txt
volleystats-0.8.1.dist-info/top_level.txt
volleystats-0.8.1.dist-info/RECORD
