Metadata-Version: 2.1
Name: volleystats
Version: 0.8.1
Summary: Command-line tool to scrape volleyball statistics from Data Project Web Competition websites
Home-page: https://github.com/claromes/volleystats
Author: Claromes
Author-email: support@claromes.com
License: GPLv3
Project-URL: Documentation, https://github.com/claromes/volleystats#documentation
Project-URL: Releases, https://github.com/claromes/volleystats/releases
Project-URL: Bug Tracker, https://github.com/claromes/volleystats/issues
Keywords: volleyball sports command-line datasets analytics
Classifier: Development Status :: 4 - Beta
Classifier: Environment :: Console
Classifier: Framework :: Scrapy
Classifier: Intended Audience :: Science/Research
Classifier: Intended Audience :: Developers
Classifier: License :: OSI Approved :: GNU General Public License v3 (GPLv3)
Classifier: Operating System :: OS Independent
Classifier: Programming Language :: Python
Classifier: Programming Language :: Python :: 3.8
Classifier: Topic :: Scientific/Engineering
Classifier: Topic :: Scientific/Engineering :: Information Analysis
Classifier: Topic :: Utilities
Requires-Python: >=3.8
License-File: LICENSE.md
Requires-Dist: scrapy ==2.11.0
